{
    "@class": "com.kony.gen.viz.model.component.KVizImage2",
    "DNDConfig": null,
    "__parentReadjusting__": false,
    "_base64_": null,
    "_height_": {
        "type": "string",
        "value": "53dp"
    },
    "_left_": {
        "type": "string",
        "value": "53dp"
    },
    "_margin_": [
        0,
        0,
        0,
        0
    ],
    "_padding_": [
        0,
        0,
        0,
        0
    ],
    "_skin_": "s8f3de8ecd464fd3a94b053c4992a8a7",
    "_src_": "touchid.png",
    "_top_": {
        "type": "string",
        "value": "14dp"
    },
    "_width_": {
        "type": "string",
        "value": "113dp"
    },
    "canUpdateUI": true,
    "containerweight": 100,
    "context": {
        "channel": "mobile",
        "formID": "Form1",
        "platform": "iphone",
        "templateType": "forms",
        "topLevelBox": null
    },
    "id": "Image0e829b31975184d",
    "imagescalemode": 1,
    "info": null,
    "invokedProperty": "src",
    "iscustomlayout": false,
    "isvisible": true,
    "kuid": "fe5a58717cdb422c884c23e40a926b5a",
    "name": "kony.ui.Image2",
    "parent": "FlexContainer0e9a8b319897e4c",
    "pf": "Form1",
    "retaincontentalignment": false,
    "retainflexpositionproperties": false,
    "srcType": 1,
    "wType": "Image",
    "widgetalignment": 5,
    "zindex": 1
}